postbook/CustomHTMLExporter.py
postbook/CustomTemplateExporter.py
postbook/PageChapter.py
postbook/__init__.py
postbook/get_list_of_files.py
postbook/main.py
postbook/make_dir_ssh.py
postbook/post.py
postbook/send_files.py
postbook/setting_the_host.py
postbook/test_main.py
postbook/update_index.py
postbook/write_html.py
postbook/write_post.py
postbook/templates/base.html.j2
postbook/templates/conf.json
postbook/templates/index.html.j2
postbook/templates/index.j2
postbook/templates/index.jinja
postbook/templates/style_pocoo.css
postbook/templates/aswins/base.html.j2
postbook/templates/aswins/blog_index.j2
postbook/templates/aswins/conf.json
postbook/templates/aswins/index.html.j2
postbook/templates/aswins/index_pocoo.html
postbook/templates/aswins/static/Link to style.css
postbook/templates/aswins/static/style.css
postbook/templates/aswins/static/style2.css
postbook/templates/aswins/static/style_pocoo.css
postbook/templates/base/celltags.j2
postbook/templates/base/display_priority.j2
postbook/templates/base/jupyter_widgets.html.j2
postbook/templates/base/mathjax.html.j2
postbook/templates/base/null.j2
postbook-0.0.4.dist-info/LICENSE
postbook-0.0.4.dist-info/METADATA
postbook-0.0.4.dist-info/WHEEL
postbook-0.0.4.dist-info/entry_points.txt
postbook-0.0.4.dist-info/top_level.txt
postbook-0.0.4.dist-info/RECORD
